hummingbird/__init__.py
hummingbird/analysis/__init__.py
hummingbird/analysis/agipd.py
hummingbird/analysis/beamline.py
hummingbird/analysis/cfel_geom.py
hummingbird/analysis/event.py
hummingbird/analysis/hitfinding.py
hummingbird/analysis/patterson.py
hummingbird/analysis/pixel_detector.py
hummingbird/analysis/recorder.py
hummingbird/analysis/sizing.py
hummingbird/analysis/stack.py
hummingbird/analysis/stxm.py
hummingbird/analysis/template.py
hummingbird/analysis/tof.py
hummingbird/analysis/tracking.py
hummingbird/backend/__init__.py
hummingbird/backend/dummy.py
hummingbird/backend/euxfel.py
hummingbird/backend/event_translator.py
hummingbird/backend/flash.py
hummingbird/backend/lcls.py
hummingbird/backend/record.py
hummingbird/backend/swissfel.py
hummingbird/backend/units.txt
hummingbird/backend/worker.py
hummingbird/backend/conf/dummy.py
hummingbird/backend/flash_utils/__init__.py
hummingbird/backend/flash_utils/convert_frms6.py
hummingbird/backend/flash_utils/holger_motors.py
hummingbird/backend/flash_utils/read_daq_offline.py
hummingbird/backend/flash_utils/tomas_motors.py
hummingbird/interface/Qt.py
hummingbird/interface/__init__.py
hummingbird/interface/colorbar.py
hummingbird/interface/data_source.py
hummingbird/interface/gui.py
hummingbird/interface/plotdata.py
hummingbird/interface/recorder.py
hummingbird/interface/ringbuffer.py
hummingbird/interface/zmqcontext.py
hummingbird/interface/zmqsocket.py
hummingbird/interface/images/logo_32.png
hummingbird/interface/images/logo_48.png
hummingbird/interface/images/logo_48_transparent.png
hummingbird/interface/images/logo_64.png
hummingbird/interface/images/logo_big.png
hummingbird/interface/images/resources.qrc
hummingbird/interface/images/resources_rc.py
hummingbird/interface/images/svg_icons/add_backend.svg
hummingbird/interface/images/svg_icons/add_image_plot.svg
hummingbird/interface/images/svg_icons/add_line_plot.svg
hummingbird/interface/images/svg_icons/recorder.svg
Hummingbird_XFEL-1.3.dist-info/LICENSE.md
Hummingbird_XFEL-1.3.dist-info/METADATA
Hummingbird_XFEL-1.3.dist-info/WHEEL
Hummingbird_XFEL-1.3.dist-info/entry_points.txt
Hummingbird_XFEL-1.3.dist-info/top_level.txt
Hummingbird_XFEL-1.3.dist-info/RECORD
