Metadata-Version: 2.1
Name: Hummingbird-XFEL
Version: 1.3
Summary: Monitoring and Analysing FXI experiments
Home-page: https://github.com/FXIhub/hummingbird
Author: Filipe R. N. C. Maia
Author-email: filipe.c.maia@gmail.com
License: BSD-2-Clause
Classifier: Development Status :: 5 - Production/Stable
Classifier: Environment :: Console
Classifier: Environment :: X11 Applications :: Qt
Classifier: Intended Audience :: Developers
Classifier: Intended Audience :: Science/Research
Classifier: License :: OSI Approved :: BSD License
Classifier: Operating System :: POSIX :: Linux
Classifier: Operating System :: MacOS
Classifier: Programming Language :: Python :: 3
Classifier: Topic :: Scientific/Engineering :: Information Analysis
Classifier: Topic :: Scientific/Engineering :: Physics
Classifier: Topic :: Scientific/Engineering :: Visualization
Requires-Python: >=3.8
License-File: LICENSE.md
Requires-Dist: h5py
Requires-Dist: h5writer
Requires-Dist: mpi4py
Requires-Dist: numpy
Requires-Dist: pexpect
Requires-Dist: Pint
Requires-Dist: PyQt5
Requires-Dist: pyqtgraph
Requires-Dist: pytz
Requires-Dist: pyzmq
Requires-Dist: scipy
Requires-Dist: tornado
Provides-Extra: docs
Requires-Dist: sphinx ; extra == 'docs'
Requires-Dist: sphinx-rtd-theme ; extra == 'docs'
Provides-Extra: euxfel
Requires-Dist: karabo-bridge ; extra == 'euxfel'
Provides-Extra: test
Requires-Dist: pytest ; extra == 'test'
Requires-Dist: pytest-cov ; extra == 'test'
Requires-Dist: codecov ; extra == 'test'
